papi_sdk/__init__.py
papi_sdk/__version__.py
papi_sdk/api_v3.py
papi_sdk/endpoints/__init__.py
papi_sdk/endpoints/endpoints.py
papi_sdk/exceptions/__init__.py
papi_sdk/exceptions/base.py
papi_sdk/models/__init__.py
papi_sdk/models/base.py
papi_sdk/models/hotel_info.py
papi_sdk/models/hotel_info_dump.py
papi_sdk/models/init_partners.py
papi_sdk/models/order_booking_finish/__init__.py
papi_sdk/models/order_booking_finish/affiliate.py
papi_sdk/models/order_booking_finish/b2b.py
papi_sdk/models/order_booking_finish/base.py
papi_sdk/models/order_booking_finish_status.py
papi_sdk/models/order_booking_form.py
papi_sdk/models/order_info/__init__.py
papi_sdk/models/order_info/affiliate.py
papi_sdk/models/order_info/b2b.py
papi_sdk/models/order_info/base.py
papi_sdk/models/overview.py
papi_sdk/models/search/__init__.py
papi_sdk/models/search/base_affiliate_response.py
papi_sdk/models/search/base_b2b_response.py
papi_sdk/models/search/base_request.py
papi_sdk/models/search/hotelpage/__init__.py
papi_sdk/models/search/hotelpage/affiliate.py
papi_sdk/models/search/hotelpage/b2b.py
papi_sdk/models/search/hotels/__init__.py
papi_sdk/models/search/hotels/affiliate.py
papi_sdk/models/search/hotels/b2b.py
papi_sdk/models/search/region/__init__.py
papi_sdk/models/search/region/affiliate.py
papi_sdk/models/search/region/b2b.py
papi_sdk/tests/__init__.py
papi_sdk/tests/mocked_data/__init__.py
papi_sdk/tests/mocked_data/affiliate_order_info.py
papi_sdk/tests/mocked_data/b2b_order_info.py
papi_sdk/tests/mocked_data/booking_order_finish.py
papi_sdk/tests/mocked_data/hotel_info.py
papi_sdk/tests/mocked_data/hotel_info_dump.py
papi_sdk/tests/mocked_data/init_partners.py
papi_sdk/tests/mocked_data/order_booking_finish_status.py
papi_sdk/tests/mocked_data/order_booking_form.py
papi_sdk/tests/mocked_data/overview.py
papi_sdk/tests/mocked_data/search_hotel_page.py
papi_sdk/tests/mocked_data/search_hotels.py
papi_sdk/tests/mocked_data/search_region.py
papi_sdk/tests/test_affiliate_order_info.py
papi_sdk-1.1.1.dist-info/LICENSE
papi_sdk-1.1.1.dist-info/WHEEL
papi_sdk-1.1.1.dist-info/METADATA
papi_sdk-1.1.1.dist-info/RECORD
