Metadata-Version: 2.1
Name: papi-sdk
Version: 1.1.1
Summary: pAPI SDK is a Python SDK for ETG APIv3
Home-page: https://github.com/emergingtravel/papi-sdk-python
License: MIT
Keywords: sdk
Author: Stanislav Losev
Author-email: stanislav.losev@ostrovok.ru
Requires-Python: >=3.6,<4.0
Classifier: License :: OSI Approved :: MIT License
Classifier: Programming Language :: Python :: 3
Classifier: Programming Language :: Python :: 3.6
Classifier: Programming Language :: Python :: 3.7
Classifier: Programming Language :: Python :: 3.8
Classifier: Programming Language :: Python :: 3.9
Classifier: Topic :: Software Development :: Libraries
Classifier: Topic :: Software Development :: Libraries :: Python Modules
Classifier: Topic :: Utilities
Requires-Dist: pydantic (>=1.7.3,<2.0.0)
Requires-Dist: requests (>=2.25.1,<3.0.0)
Project-URL: Repository, https://github.com/emergingtravel/papi-sdk-python
